qecore/__init__.py
qecore/api.py
qecore/application.py
qecore/common_steps.py
qecore/flatpak.py
qecore/get_node.py
qecore/icons.py
qecore/image_matching.py
qecore/logger.py
qecore/online_accounts.py
qecore/sandbox.py
qecore/step_matcher.py
qecore/utility.py
qecore-4.11.data/scripts/qecore
qecore-4.11.data/scripts/qecore-config
qecore-4.11.data/scripts/qecore-headless
qecore-4.11.data/scripts/qecore-runtest
qecore-4.11.data/scripts/qecore_backtrace_from_coredump
qecore-4.11.data/scripts/qecore_bash_completion
qecore-4.11.data/scripts/qecore_capture_screenshot
qecore-4.11.data/scripts/qecore_capture_window_screenshot
qecore-4.11.data/scripts/qecore_create_keyring
qecore-4.11.data/scripts/qecore_get_active_display
qecore-4.11.data/scripts/qecore_help
qecore-4.11.data/scripts/qecore_start_recording
qecore-4.11.dist-info/licenses/LICENSE
qecore-4.11.dist-info/METADATA
qecore-4.11.dist-info/WHEEL
qecore-4.11.dist-info/top_level.txt
qecore-4.11.dist-info/RECORD
