Metadata-Version: 2.4
Name: qecore
Version: 4.11
Summary: DesktopQE Tool for unified test execution
Home-page: https://gitlab.com/dogtail/qecore
Author: Michal Odehnal
Author-email: modehnal@redhat.com
License: GPLv3
Classifier: Intended Audience :: Developers
Classifier: License :: OSI Approved :: GNU General Public License v3 (GPLv3)
Classifier: Operating System :: OS Independent
Classifier: Programming Language :: Python :: 3.6
Classifier: Programming Language :: Python :: 3.7
Classifier: Programming Language :: Python :: 3.8
Classifier: Programming Language :: Python :: 3.9
Classifier: Programming Language :: Python :: 3.10
Classifier: Programming Language :: Python :: 3.11
Classifier: Programming Language :: Python :: 3.12
Classifier: Programming Language :: Python :: 3.13
Classifier: Programming Language :: Python :: Implementation :: PyPy
Classifier: Topic :: Software Development :: Testing
Classifier: Topic :: Software Development :: Testing :: BDD
Requires-Python: >=3.6
License-File: LICENSE
Requires-Dist: behave>=1.3.0
Requires-Dist: behave-html-formatter<=0.9.10
Requires-Dist: behave-html-pretty-formatter
Requires-Dist: dasbus<=1.7
Dynamic: author
Dynamic: author-email
Dynamic: classifier
Dynamic: description
Dynamic: description-content-type
Dynamic: home-page
Dynamic: license
Dynamic: license-file
Dynamic: requires-dist
Dynamic: requires-python
Dynamic: summary
